inventory_optimizer_package_23384069/__init__.py
inventory_optimizer_package_23384069/optimizer.py
inventory_optimizer_package_23384069-1.1.4.dist-info/METADATA
inventory_optimizer_package_23384069-1.1.4.dist-info/WHEEL
inventory_optimizer_package_23384069-1.1.4.dist-info/licenses/LICENSE
inventory_optimizer_package_23384069-1.1.4.dist-info/RECORD
