Metadata-Version: 2.3
Name: inventory-optimizer-package-23384069
Version: 1.1.4
Summary: A simple package that ensures stock level in inventory is always optimal
Project-URL: Homepage, https://github.com/Ughanze23/CPP-PROJECT/tree/main/inventory_optimizer
Author-email: Ikenna Ughanze <ughanzepolycarp@example.com>
Classifier: License :: OSI Approved :: MIT License
Classifier: Operating System :: OS Independent
Classifier: Programming Language :: Python :: 3
Requires-Python: >=3.8
Requires-Dist: django>=3.2
